tests/__init__.py
tests/test_converter.py
year_extractor/__init__.py
year_extractor/converter.py
year_extractor-2.1.0.dist-info/LICENSE
year_extractor-2.1.0.dist-info/METADATA
year_extractor-2.1.0.dist-info/WHEEL
year_extractor-2.1.0.dist-info/top_level.txt
year_extractor-2.1.0.dist-info/RECORD
